sclass.py
sclass-1.0.0.dist-info/DESCRIPTION.rst
sclass-1.0.0.dist-info/METADATA
sclass-1.0.0.dist-info/RECORD
sclass-1.0.0.dist-info/WHEEL
sclass-1.0.0.dist-info/metadata.json
sclass-1.0.0.dist-info/top_level.txt
