Metadata-Version: 2.0
Name: sclass
Version: 1.0.0
Summary: Basic class used as a SuperClass for other classes
Home-page: UNKNOWN
Author: Lorenzo Bartolini
Author-email: l.bartolini02@gmail.com
License: UNKNOWN
Platform: UNKNOWN
Classifier: Programming Language :: Python :: 3.6
Classifier: Operating System :: OS Independent
